{"nodes": [{"id": "d_project_financetracker_backend_app_services_summary_py", "label": "summary.py", "file_type": "code", "source_file": "backend/app/services/summary.py", "source_location": "L1"}, {"id": "d_project_financetracker_backend_app_services_summary_to_local", "label": "_to_local()", "file_type": "code", "source_file": "backend/app/services/summary.py", "source_location": "L13", "_callable": true}, {"id": "datetime", "label": "datetime", "file_type": "code", "source_file": "", "source_location": "", "origin_file": "D:\\Project\\financeTracker\\backend\\app\\services\\summary.py"}, {"id": "d_project_financetracker_backend_app_services_summary_categorytotal", "label": "CategoryTotal", "file_type": "code", "source_file": "backend/app/services/summary.py", "source_location": "L21", "_callable": true}, {"id": "d_project_financetracker_backend_app_services_summary_periodsummary", "label": "PeriodSummary", "file_type": "code", "source_file": "backend/app/services/summary.py", "source_location": "L27", "_callable": true}, {"id": "d_project_financetracker_backend_app_services_summary_period_summary", "label": "period_summary()", "file_type": "code", "source_file": "backend/app/services/summary.py", "source_location": "L34", "_callable": true}, {"id": "session", "label": "Session", "file_type": "code", "source_file": "", "source_location": "", "origin_file": "D:\\Project\\financeTracker\\backend\\app\\services\\summary.py"}, {"id": "d_project_financetracker_backend_app_services_summary_spendingcomparison", "label": "SpendingComparison", "file_type": "code", "source_file": "backend/app/services/summary.py", "source_location": "L71", "_callable": true}, {"id": "d_project_financetracker_backend_app_services_summary_prev_ym", "label": "_prev_ym()", "file_type": "code", "source_file": "backend/app/services/summary.py", "source_location": "L82", "_callable": true}, {"id": "d_project_financetracker_backend_app_services_summary_spending_comparison", "label": "spending_comparison()", "file_type": "code", "source_file": "backend/app/services/summary.py", "source_location": "L86", "_callable": true}, {"id": "d_project_financetracker_backend_app_services_summary_monthpoint", "label": "MonthPoint", "file_type": "code", "source_file": "backend/app/services/summary.py", "source_location": "L125", "_callable": true}, {"id": "d_project_financetracker_backend_app_services_summary_month_bounds", "label": "_month_bounds()", "file_type": "code", "source_file": "backend/app/services/summary.py", "source_location": "L131", "_callable": true}, {"id": "d_project_financetracker_backend_app_services_summary_monthly_trend", "label": "monthly_trend()", "file_type": "code", "source_file": "backend/app/services/summary.py", "source_location": "L138", "_callable": true}, {"id": "d_project_financetracker_backend_app_services_summary_daily_expense", "label": "daily_expense()", "file_type": "code", "source_file": "backend/app/services/summary.py", "source_location": "L173", "_callable": true}, {"id": "decimal", "label": "Decimal", "file_type": "code", "source_file": "", "source_location": "", "origin_file": "D:\\Project\\financeTracker\\backend\\app\\services\\summary.py"}, {"id": "d_project_financetracker_backend_app_services_summary_merchantstat", "label": "MerchantStat", "file_type": "code", "source_file": "backend/app/services/summary.py", "source_location": "L192", "_callable": true}, {"id": "d_project_financetracker_backend_app_services_summary_top_merchants", "label": "top_merchants()", "file_type": "code", "source_file": "backend/app/services/summary.py", "source_location": "L198", "_callable": true}, {"id": "d_project_financetracker_backend_app_services_summary_rationale_14", "label": "Normalkan ke zona lokal. Datetime naif dianggap UTC (kasus SQLite).", "file_type": "rationale", "source_file": "backend/app/services/summary.py", "source_location": "L14"}, {"id": "d_project_financetracker_backend_app_services_summary_rationale_87", "label": "Bandingkan pengeluaran bulan (year, mon) vs bulan sebelumnya, plus kategori", "file_type": "rationale", "source_file": "backend/app/services/summary.py", "source_location": "L87"}, {"id": "d_project_financetracker_backend_app_services_summary_rationale_139", "label": "Tren `months` bulan terakhir sampai bulan `ref` (kronologis menaik).", "file_type": "rationale", "source_file": "backend/app/services/summary.py", "source_location": "L139"}, {"id": "d_project_financetracker_backend_app_services_summary_rationale_174", "label": "Total pengeluaran per tanggal (1..akhir bulan) untuk heatmap kalender.", "file_type": "rationale", "source_file": "backend/app/services/summary.py", "source_location": "L174"}, {"id": "d_project_financetracker_backend_app_services_summary_rationale_201", "label": "Merchant terbanyak dari transaksi yang punya struk (data OCR).", "file_type": "rationale", "source_file": "backend/app/services/summary.py", "source_location": "L201"}], "edges": [{"source": "d_project_financetracker_backend_app_services_summary_py", "target": "calendar", "relation": "imports_from", "context": "import", "confidence": "EXTRACTED", "source_file": "backend/app/services/summary.py", "source_location": "L1", "weight": 1.0}, {"source": "d_project_financetracker_backend_app_services_summary_py", "target": "dataclasses", "relation": "imports_from", "context": "import", "confidence": "EXTRACTED", "source_file": "backend/app/services/summary.py", "source_location": "L2", "weight": 1.0}, {"source": "d_project_financetracker_backend_app_services_summary_py", "target": "datetime", "relation": "imports_from", "context": "import", "confidence": "EXTRACTED", "source_file": "backend/app/services/summary.py", "source_location": "L3", "weight": 1.0}, {"source": "d_project_financetracker_backend_app_services_summary_py", "target": "decimal", "relation": "imports_from", "context": "import", "confidence": "EXTRACTED", "source_file": "backend/app/services/summary.py", "source_location": "L4", "weight": 1.0}, {"source": "d_project_financetracker_backend_app_services_summary_py", "target": "sqlalchemy", "relation": "imports_from", "context": "import", "confidence": "EXTRACTED", "source_file": "backend/app/services/summary.py", "source_location": "L6", "weight": 1.0}, {"source": "d_project_financetracker_backend_app_services_summary_py", "target": "sqlalchemy_orm", "relation": "imports_from", "context": "import", "confidence": "EXTRACTED", "source_file": "backend/app/services/summary.py", "source_location": "L7", "weight": 1.0}, {"source": "d_project_financetracker_backend_app_services_summary_py", "target": "app_core_clock", "relation": "imports_from", "context": "import", "confidence": "EXTRACTED", "source_file": "backend/app/services/summary.py", "source_location": "L9", "weight": 1.0}, {"source": "d_project_financetracker_backend_app_services_summary_py", "target": "app_models", "relation": "imports_from", "context": "import", "confidence": "EXTRACTED", "source_file": "backend/app/services/summary.py", "source_location": "L10", "weight": 1.0}, {"source": "d_project_financetracker_backend_app_services_summary_py", "target": "d_project_financetracker_backend_app_services_summary_to_local", "relation": "contains", "confidence": "EXTRACTED", "source_file": "backend/app/services/summary.py", "source_location": "L13", "weight": 1.0}, {"source": "d_project_financetracker_backend_app_services_summary_to_local", "target": "datetime", "relation": "references", "context": "parameter_type", "confidence": "EXTRACTED", "source_file": "backend/app/services/summary.py", "source_location": "L13", "weight": 1.0}, {"source": "d_project_financetracker_backend_app_services_summary_to_local", "target": "datetime", "relation": "references", "context": "return_type", "confidence": "EXTRACTED", "source_file": "backend/app/services/summary.py", "source_location": "L13", "weight": 1.0}, {"source": "d_project_financetracker_backend_app_services_summary_py", "target": "d_project_financetracker_backend_app_services_summary_categorytotal", "relation": "contains", "confidence": "EXTRACTED", "source_file": "backend/app/services/summary.py", "source_location": "L21", "weight": 1.0}, {"source": "d_project_financetracker_backend_app_services_summary_py", "target": "d_project_financetracker_backend_app_services_summary_periodsummary", "relation": "contains", "confidence": "EXTRACTED", "source_file": "backend/app/services/summary.py", "source_location": "L27", "weight": 1.0}, {"source": "d_project_financetracker_backend_app_services_summary_py", "target": "d_project_financetracker_backend_app_services_summary_period_summary", "relation": "contains", "confidence": "EXTRACTED", "source_file": "backend/app/services/summary.py", "source_location": "L34", "weight": 1.0}, {"source": "d_project_financetracker_backend_app_services_summary_period_summary", "target": "session", "relation": "references", "context": "parameter_type", "confidence": "EXTRACTED", "source_file": "backend/app/services/summary.py", "source_location": "L34", "weight": 1.0}, {"source": "d_project_financetracker_backend_app_services_summary_period_summary", "target": "datetime", "relation": "references", "context": "parameter_type", "confidence": "EXTRACTED", "source_file": "backend/app/services/summary.py", "source_location": "L34", "weight": 1.0}, {"source": "d_project_financetracker_backend_app_services_summary_period_summary", "target": "datetime", "relation": "references", "context": "parameter_type", "confidence": "EXTRACTED", "source_file": "backend/app/services/summary.py", "source_location": "L34", "weight": 1.0}, {"source": "d_project_financetracker_backend_app_services_summary_period_summary", "target": "d_project_financetracker_backend_app_services_summary_periodsummary", "relation": "references", "context": "return_type", "confidence": "EXTRACTED", "source_file": "backend/app/services/summary.py", "source_location": "L34", "weight": 1.0}, {"source": "d_project_financetracker_backend_app_services_summary_py", "target": "d_project_financetracker_backend_app_services_summary_spendingcomparison", "relation": "contains", "confidence": "EXTRACTED", "source_file": "backend/app/services/summary.py", "source_location": "L71", "weight": 1.0}, {"source": "d_project_financetracker_backend_app_services_summary_py", "target": "d_project_financetracker_backend_app_services_summary_prev_ym", "relation": "contains", "confidence": "EXTRACTED", "source_file": "backend/app/services/summary.py", "source_location": "L82", "weight": 1.0}, {"source": "d_project_financetracker_backend_app_services_summary_py", "target": "d_project_financetracker_backend_app_services_summary_spending_comparison", "relation": "contains", "confidence": "EXTRACTED", "source_file": "backend/app/services/summary.py", "source_location": "L86", "weight": 1.0}, {"source": "d_project_financetracker_backend_app_services_summary_spending_comparison", "target": "session", "relation": "references", "context": "parameter_type", "confidence": "EXTRACTED", "source_file": "backend/app/services/summary.py", "source_location": "L86", "weight": 1.0}, {"source": "d_project_financetracker_backend_app_services_summary_spending_comparison", "target": "d_project_financetracker_backend_app_services_summary_spendingcomparison", "relation": "references", "context": "return_type", "confidence": "EXTRACTED", "source_file": "backend/app/services/summary.py", "source_location": "L86", "weight": 1.0}, {"source": "d_project_financetracker_backend_app_services_summary_py", "target": "d_project_financetracker_backend_app_services_summary_monthpoint", "relation": "contains", "confidence": "EXTRACTED", "source_file": "backend/app/services/summary.py", "source_location": "L125", "weight": 1.0}, {"source": "d_project_financetracker_backend_app_services_summary_py", "target": "d_project_financetracker_backend_app_services_summary_month_bounds", "relation": "contains", "confidence": "EXTRACTED", "source_file": "backend/app/services/summary.py", "source_location": "L131", "weight": 1.0}, {"source": "d_project_financetracker_backend_app_services_summary_month_bounds", "target": "datetime", "relation": "references", "context": "generic_arg", "confidence": "EXTRACTED", "source_file": "backend/app/services/summary.py", "source_location": "L131", "weight": 1.0}, {"source": "d_project_financetracker_backend_app_services_summary_month_bounds", "target": "datetime", "relation": "references", "context": "generic_arg", "confidence": "EXTRACTED", "source_file": "backend/app/services/summary.py", "source_location": "L131", "weight": 1.0}, {"source": "d_project_financetracker_backend_app_services_summary_py", "target": "d_project_financetracker_backend_app_services_summary_monthly_trend", "relation": "contains", "confidence": "EXTRACTED", "source_file": "backend/app/services/summary.py", "source_location": "L138", "weight": 1.0}, {"source": "d_project_financetracker_backend_app_services_summary_monthly_trend", "target": "session", "relation": "references", "context": "parameter_type", "confidence": "EXTRACTED", "source_file": "backend/app/services/summary.py", "source_location": "L138", "weight": 1.0}, {"source": "d_project_financetracker_backend_app_services_summary_monthly_trend", "target": "datetime", "relation": "references", "context": "parameter_type", "confidence": "EXTRACTED", "source_file": "backend/app/services/summary.py", "source_location": "L138", "weight": 1.0}, {"source": "d_project_financetracker_backend_app_services_summary_monthly_trend", "target": "d_project_financetracker_backend_app_services_summary_monthpoint", "relation": "references", "context": "generic_arg", "confidence": "EXTRACTED", "source_file": "backend/app/services/summary.py", "source_location": "L138", "weight": 1.0}, {"source": "d_project_financetracker_backend_app_services_summary_py", "target": "d_project_financetracker_backend_app_services_summary_daily_expense", "relation": "contains", "confidence": "EXTRACTED", "source_file": "backend/app/services/summary.py", "source_location": "L173", "weight": 1.0}, {"source": "d_project_financetracker_backend_app_services_summary_daily_expense", "target": "session", "relation": "references", "context": "parameter_type", "confidence": "EXTRACTED", "source_file": "backend/app/services/summary.py", "source_location": "L173", "weight": 1.0}, {"source": "d_project_financetracker_backend_app_services_summary_daily_expense", "target": "decimal", "relation": "references", "context": "generic_arg", "confidence": "EXTRACTED", "source_file": "backend/app/services/summary.py", "source_location": "L173", "weight": 1.0}, {"source": "d_project_financetracker_backend_app_services_summary_py", "target": "d_project_financetracker_backend_app_services_summary_merchantstat", "relation": "contains", "confidence": "EXTRACTED", "source_file": "backend/app/services/summary.py", "source_location": "L192", "weight": 1.0}, {"source": "d_project_financetracker_backend_app_services_summary_py", "target": "d_project_financetracker_backend_app_services_summary_top_merchants", "relation": "contains", "confidence": "EXTRACTED", "source_file": "backend/app/services/summary.py", "source_location": "L198", "weight": 1.0}, {"source": "d_project_financetracker_backend_app_services_summary_top_merchants", "target": "session", "relation": "references", "context": "parameter_type", "confidence": "EXTRACTED", "source_file": "backend/app/services/summary.py", "source_location": "L198", "weight": 1.0}, {"source": "d_project_financetracker_backend_app_services_summary_top_merchants", "target": "d_project_financetracker_backend_app_services_summary_merchantstat", "relation": "references", "context": "generic_arg", "confidence": "EXTRACTED", "source_file": "backend/app/services/summary.py", "source_location": "L198", "weight": 1.0}, {"source": "d_project_financetracker_backend_app_services_summary_period_summary", "target": "d_project_financetracker_backend_app_services_summary_periodsummary", "relation": "calls", "context": "call", "confidence": "EXTRACTED", "source_file": "backend/app/services/summary.py", "source_location": "L48", "weight": 1.0}, {"source": "d_project_financetracker_backend_app_services_summary_period_summary", "target": "decimal", "relation": "calls", "context": "call", "confidence": "EXTRACTED", "source_file": "backend/app/services/summary.py", "source_location": "L51", "weight": 1.0}, {"source": "d_project_financetracker_backend_app_services_summary_period_summary", "target": "d_project_financetracker_backend_app_services_summary_categorytotal", "relation": "calls", "context": "call", "confidence": "EXTRACTED", "source_file": "backend/app/services/summary.py", "source_location": "L66", "weight": 1.0}, {"source": "d_project_financetracker_backend_app_services_summary_spending_comparison", "target": "d_project_financetracker_backend_app_services_summary_prev_ym", "relation": "calls", "context": "call", "confidence": "EXTRACTED", "source_file": "backend/app/services/summary.py", "source_location": "L89", "weight": 1.0}, {"source": "d_project_financetracker_backend_app_services_summary_spending_comparison", "target": "d_project_financetracker_backend_app_services_summary_period_summary", "relation": "calls", "context": "call", "confidence": "EXTRACTED", "source_file": "backend/app/services/summary.py", "source_location": "L90", "weight": 1.0}, {"source": "d_project_financetracker_backend_app_services_summary_spending_comparison", "target": "d_project_financetracker_backend_app_services_summary_month_bounds", "relation": "calls", "context": "call", "confidence": "EXTRACTED", "source_file": "backend/app/services/summary.py", "source_location": "L90", "weight": 1.0}, {"source": "d_project_financetracker_backend_app_services_summary_spending_comparison", "target": "decimal", "relation": "calls", "context": "call", "confidence": "EXTRACTED", "source_file": "backend/app/services/summary.py", "source_location": "L97", "weight": 1.0}, {"source": "d_project_financetracker_backend_app_services_summary_spending_comparison", "target": "d_project_financetracker_backend_app_services_summary_spendingcomparison", "relation": "calls", "context": "call", "confidence": "EXTRACTED", "source_file": "backend/app/services/summary.py", "source_location": "L112", "weight": 1.0}, {"source": "d_project_financetracker_backend_app_services_summary_month_bounds", "target": "datetime", "relation": "calls", "context": "call", "confidence": "EXTRACTED", "source_file": "backend/app/services/summary.py", "source_location": "L132", "weight": 1.0}, {"source": "d_project_financetracker_backend_app_services_summary_monthly_trend", "target": "d_project_financetracker_backend_app_services_summary_month_bounds", "relation": "calls", "context": "call", "confidence": "EXTRACTED", "source_file": "backend/app/services/summary.py", "source_location": "L152", "weight": 1.0}, {"source": "d_project_financetracker_backend_app_services_summary_monthly_trend", "target": "decimal", "relation": "calls", "context": "call", "confidence": "EXTRACTED", "source_file": "backend/app/services/summary.py", "source_location": "L162", "weight": 1.0}, {"source": "d_project_financetracker_backend_app_services_summary_monthly_trend", "target": "d_project_financetracker_backend_app_services_summary_monthpoint", "relation": "calls", "context": "call", "confidence": "EXTRACTED", "source_file": "backend/app/services/summary.py", "source_location": "L164", "weight": 1.0}, {"source": "d_project_financetracker_backend_app_services_summary_daily_expense", "target": "d_project_financetracker_backend_app_services_summary_month_bounds", "relation": "calls", "context": "call", "confidence": "EXTRACTED", "source_file": "backend/app/services/summary.py", "source_location": "L175", "weight": 1.0}, {"source": "d_project_financetracker_backend_app_services_summary_daily_expense", "target": "d_project_financetracker_backend_app_services_summary_to_local", "relation": "calls", "context": "call", "confidence": "EXTRACTED", "source_file": "backend/app/services/summary.py", "source_location": "L186", "weight": 1.0}, {"source": "d_project_financetracker_backend_app_services_summary_daily_expense", "target": "decimal", "relation": "calls", "context": "call", "confidence": "EXTRACTED", "source_file": "backend/app/services/summary.py", "source_location": "L187", "weight": 1.0}, {"source": "d_project_financetracker_backend_app_services_summary_top_merchants", "target": "d_project_financetracker_backend_app_services_summary_month_bounds", "relation": "calls", "context": "call", "confidence": "EXTRACTED", "source_file": "backend/app/services/summary.py", "source_location": "L202", "weight": 1.0}, {"source": "d_project_financetracker_backend_app_services_summary_top_merchants", "target": "d_project_financetracker_backend_app_services_summary_merchantstat", "relation": "calls", "context": "call", "confidence": "EXTRACTED", "source_file": "backend/app/services/summary.py", "source_location": "L221", "weight": 1.0}, {"source": "d_project_financetracker_backend_app_services_summary_top_merchants", "target": "decimal", "relation": "calls", "context": "call", "confidence": "EXTRACTED", "source_file": "backend/app/services/summary.py", "source_location": "L221", "weight": 1.0}, {"source": "d_project_financetracker_backend_app_services_summary_rationale_14", "target": "d_project_financetracker_backend_app_services_summary_to_local", "relation": "rationale_for", "confidence": "EXTRACTED", "source_file": "backend/app/services/summary.py", "source_location": "L14", "weight": 1.0}, {"source": "d_project_financetracker_backend_app_services_summary_rationale_87", "target": "d_project_financetracker_backend_app_services_summary_spending_comparison", "relation": "rationale_for", "confidence": "EXTRACTED", "source_file": "backend/app/services/summary.py", "source_location": "L87", "weight": 1.0}, {"source": "d_project_financetracker_backend_app_services_summary_rationale_139", "target": "d_project_financetracker_backend_app_services_summary_monthly_trend", "relation": "rationale_for", "confidence": "EXTRACTED", "source_file": "backend/app/services/summary.py", "source_location": "L139", "weight": 1.0}, {"source": "d_project_financetracker_backend_app_services_summary_rationale_174", "target": "d_project_financetracker_backend_app_services_summary_daily_expense", "relation": "rationale_for", "confidence": "EXTRACTED", "source_file": "backend/app/services/summary.py", "source_location": "L174", "weight": 1.0}, {"source": "d_project_financetracker_backend_app_services_summary_rationale_201", "target": "d_project_financetracker_backend_app_services_summary_top_merchants", "relation": "rationale_for", "confidence": "EXTRACTED", "source_file": "backend/app/services/summary.py", "source_location": "L201", "weight": 1.0}], "raw_calls": [{"caller_nid": "d_project_financetracker_backend_app_services_summary_to_local", "callee": "replace", "is_member_call": true, "source_file": "backend/app/services/summary.py", "source_location": "L16", "receiver": "dt"}, {"caller_nid": "d_project_financetracker_backend_app_services_summary_to_local", "callee": "astimezone", "is_member_call": true, "source_file": "backend/app/services/summary.py", "source_location": "L17", "receiver": "dt"}, {"caller_nid": "d_project_financetracker_backend_app_services_summary_to_local", "callee": "LOCAL_TZ", "is_member_call": false, "indirect": true, "context": "argument", "source_file": "backend/app/services/summary.py", "source_location": "L17"}, {"caller_nid": "d_project_financetracker_backend_app_services_summary_period_summary", "callee": "execute", "is_member_call": true, "source_file": "backend/app/services/summary.py", "source_location": "L43", "receiver": "db"}, {"caller_nid": "d_project_financetracker_backend_app_services_summary_period_summary", "callee": "group_by", "is_member_call": true, "source_file": "backend/app/services/summary.py", "source_location": "L44", "receiver": null}, {"caller_nid": "d_project_financetracker_backend_app_services_summary_period_summary", "callee": "where", "is_member_call": true, "source_file": "backend/app/services/summary.py", "source_location": "L44", "receiver": null}, {"caller_nid": "d_project_financetracker_backend_app_services_summary_period_summary", "callee": "select", "is_member_call": false, "source_file": "backend/app/services/summary.py", "source_location": "L44", "receiver": null}, {"caller_nid": "d_project_financetracker_backend_app_services_summary_period_summary", "callee": "coalesce", "is_member_call": true, "source_file": "backend/app/services/summary.py", "source_location": "L44", "receiver": "func"}, {"caller_nid": "d_project_financetracker_backend_app_services_summary_period_summary", "callee": "scalar", "is_member_call": true, "source_file": "backend/app/services/summary.py", "source_location": "L55", "receiver": "db"}, {"caller_nid": "d_project_financetracker_backend_app_services_summary_period_summary", "callee": "where", "is_member_call": true, "source_file": "backend/app/services/summary.py", "source_location": "L56", "receiver": null}, {"caller_nid": "d_project_financetracker_backend_app_services_summary_period_summary", "callee": "select_from", "is_member_call": true, "source_file": "backend/app/services/summary.py", "source_location": "L56", "receiver": null}, {"caller_nid": "d_project_financetracker_backend_app_services_summary_period_summary", "callee": "Transaction", "is_member_call": false, "indirect": true, "context": "argument", "source_file": "backend/app/services/summary.py", "source_location": "L56"}, {"caller_nid": "d_project_financetracker_backend_app_services_summary_period_summary", "callee": "select", "is_member_call": false, "source_file": "backend/app/services/summary.py", "source_location": "L56", "receiver": null}, {"caller_nid": "d_project_financetracker_backend_app_services_summary_period_summary", "callee": "count", "is_member_call": true, "source_file": "backend/app/services/summary.py", "source_location": "L56", "receiver": "func"}, {"caller_nid": "d_project_financetracker_backend_app_services_summary_period_summary", "callee": "execute", "is_member_call": true, "source_file": "backend/app/services/summary.py", "source_location": "L59", "receiver": "db"}, {"caller_nid": "d_project_financetracker_backend_app_services_summary_period_summary", "callee": "order_by", "is_member_call": true, "source_file": "backend/app/services/summary.py", "source_location": "L60", "receiver": null}, {"caller_nid": "d_project_financetracker_backend_app_services_summary_period_summary", "callee": "group_by", "is_member_call": true, "source_file": "backend/app/services/summary.py", "source_location": "L60", "receiver": null}, {"caller_nid": "d_project_financetracker_backend_app_services_summary_period_summary", "callee": "where", "is_member_call": true, "source_file": "backend/app/services/summary.py", "source_location": "L60", "receiver": null}, {"caller_nid": "d_project_financetracker_backend_app_services_summary_period_summary", "callee": "join", "is_member_call": true, "source_file": "backend/app/services/summary.py", "source_location": "L60", "receiver": null}, {"caller_nid": "d_project_financetracker_backend_app_services_summary_period_summary", "callee": "Category", "is_member_call": false, "indirect": true, "context": "argument", "source_file": "backend/app/services/summary.py", "source_location": "L61"}, {"caller_nid": "d_project_financetracker_backend_app_services_summary_period_summary", "callee": "select", "is_member_call": false, "source_file": "backend/app/services/summary.py", "source_location": "L60", "receiver": null}, {"caller_nid": "d_project_financetracker_backend_app_services_summary_period_summary", "callee": "desc", "is_member_call": true, "source_file": "backend/app/services/summary.py", "source_location": "L64", "receiver": null}, {"caller_nid": "d_project_financetracker_backend_app_services_summary_spending_comparison", "callee": "get", "is_member_call": true, "source_file": "backend/app/services/summary.py", "source_location": "L97", "receiver": "cur_map"}, {"caller_nid": "d_project_financetracker_backend_app_services_summary_spending_comparison", "callee": "get", "is_member_call": true, "source_file": "backend/app/services/summary.py", "source_location": "L97", "receiver": "prev_map"}, {"caller_nid": "d_project_financetracker_backend_app_services_summary_spending_comparison", "callee": "items", "is_member_call": true, "source_file": "backend/app/services/summary.py", "source_location": "L100", "receiver": "deltas"}, {"caller_nid": "d_project_financetracker_backend_app_services_summary_spending_comparison", "callee": "to_integral_value", "is_member_call": true, "source_file": "backend/app/services/summary.py", "source_location": "L108", "receiver": null}, {"caller_nid": "d_project_financetracker_backend_app_services_summary_month_bounds", "callee": "LOCAL_TZ", "is_member_call": false, "indirect": true, "context": "argument", "source_file": "backend/app/services/summary.py", "source_location": "L132"}, {"caller_nid": "d_project_financetracker_backend_app_services_summary_month_bounds", "callee": "monthrange", "is_member_call": false, "source_file": "backend/app/services/summary.py", "source_location": "L133", "receiver": null}, {"caller_nid": "d_project_financetracker_backend_app_services_summary_month_bounds", "callee": "LOCAL_TZ", "is_member_call": false, "indirect": true, "context": "argument", "source_file": "backend/app/services/summary.py", "source_location": "L134"}, {"caller_nid": "d_project_financetracker_backend_app_services_summary_monthly_trend", "callee": "append", "is_member_call": true, "source_file": "backend/app/services/summary.py", "source_location": "L143", "receiver": "seq"}, {"caller_nid": "d_project_financetracker_backend_app_services_summary_monthly_trend", "callee": "reverse", "is_member_call": true, "source_file": "backend/app/services/summary.py", "source_location": "L148", "receiver": "seq"}, {"caller_nid": "d_project_financetracker_backend_app_services_summary_monthly_trend", "callee": "execute", "is_member_call": true, "source_file": "backend/app/services/summary.py", "source_location": "L153", "receiver": "db"}, {"caller_nid": "d_project_financetracker_backend_app_services_summary_monthly_trend", "callee": "group_by", "is_member_call": true, "source_file": "backend/app/services/summary.py", "source_location": "L154", "receiver": null}, {"caller_nid": "d_project_financetracker_backend_app_services_summary_monthly_trend", "callee": "where", "is_member_call": true, "source_file": "backend/app/services/summary.py", "source_location": "L154", "receiver": null}, {"caller_nid": "d_project_financetracker_backend_app_services_summary_monthly_trend", "callee": "select", "is_member_call": false, "source_file": "backend/app/services/summary.py", "source_location": "L154", "receiver": null}, {"caller_nid": "d_project_financetracker_backend_app_services_summary_monthly_trend", "callee": "coalesce", "is_member_call": true, "source_file": "backend/app/services/summary.py", "source_location": "L154", "receiver": "func"}, {"caller_nid": "d_project_financetracker_backend_app_services_summary_monthly_trend", "callee": "append", "is_member_call": true, "source_file": "backend/app/services/summary.py", "source_location": "L163", "receiver": "points"}, {"caller_nid": "d_project_financetracker_backend_app_services_summary_monthly_trend", "callee": "get", "is_member_call": true, "source_file": "backend/app/services/summary.py", "source_location": "L166", "receiver": "totals"}, {"caller_nid": "d_project_financetracker_backend_app_services_summary_monthly_trend", "callee": "get", "is_member_call": true, "source_file": "backend/app/services/summary.py", "source_location": "L167", "receiver": "totals"}, {"caller_nid": "d_project_financetracker_backend_app_services_summary_daily_expense", "callee": "execute", "is_member_call": true, "source_file": "backend/app/services/summary.py", "source_location": "L176", "receiver": "db"}, {"caller_nid": "d_project_financetracker_backend_app_services_summary_daily_expense", "callee": "where", "is_member_call": true, "source_file": "backend/app/services/summary.py", "source_location": "L177", "receiver": null}, {"caller_nid": "d_project_financetracker_backend_app_services_summary_daily_expense", "callee": "select", "is_member_call": false, "source_file": "backend/app/services/summary.py", "source_location": "L177", "receiver": null}, {"caller_nid": "d_project_financetracker_backend_app_services_summary_daily_expense", "callee": "get", "is_member_call": true, "source_file": "backend/app/services/summary.py", "source_location": "L187", "receiver": "out"}, {"caller_nid": "d_project_financetracker_backend_app_services_summary_top_merchants", "callee": "execute", "is_member_call": true, "source_file": "backend/app/services/summary.py", "source_location": "L203", "receiver": "db"}, {"caller_nid": "d_project_financetracker_backend_app_services_summary_top_merchants", "callee": "limit", "is_member_call": true, "source_file": "backend/app/services/summary.py", "source_location": "L204", "receiver": null}, {"caller_nid": "d_project_financetracker_backend_app_services_summary_top_merchants", "callee": "order_by", "is_member_call": true, "source_file": "backend/app/services/summary.py", "source_location": "L204", "receiver": null}, {"caller_nid": "d_project_financetracker_backend_app_services_summary_top_merchants", "callee": "group_by", "is_member_call": true, "source_file": "backend/app/services/summary.py", "source_location": "L204", "receiver": null}, {"caller_nid": "d_project_financetracker_backend_app_services_summary_top_merchants", "callee": "where", "is_member_call": true, "source_file": "backend/app/services/summary.py", "source_location": "L204", "receiver": null}, {"caller_nid": "d_project_financetracker_backend_app_services_summary_top_merchants", "callee": "join", "is_member_call": true, "source_file": "backend/app/services/summary.py", "source_location": "L204", "receiver": null}, {"caller_nid": "d_project_financetracker_backend_app_services_summary_top_merchants", "callee": "Receipt", "is_member_call": false, "indirect": true, "context": "argument", "source_file": "backend/app/services/summary.py", "source_location": "L209"}, {"caller_nid": "d_project_financetracker_backend_app_services_summary_top_merchants", "callee": "select", "is_member_call": false, "source_file": "backend/app/services/summary.py", "source_location": "L204", "receiver": null}, {"caller_nid": "d_project_financetracker_backend_app_services_summary_top_merchants", "callee": "count", "is_member_call": true, "source_file": "backend/app/services/summary.py", "source_location": "L207", "receiver": "func"}, {"caller_nid": "d_project_financetracker_backend_app_services_summary_top_merchants", "callee": "is_not", "is_member_call": true, "source_file": "backend/app/services/summary.py", "source_location": "L215", "receiver": null}, {"caller_nid": "d_project_financetracker_backend_app_services_summary_top_merchants", "callee": "desc", "is_member_call": true, "source_file": "backend/app/services/summary.py", "source_location": "L218", "receiver": null}]}